dashai_plugin_test_cami/__init__.py
dashai_plugin_test_cami/dataloader_class_template.py
dashai_plugin_test_cami/metric_class_template.py
dashai_plugin_test_cami/mlp_pytorch_model.py
dashai_plugin_test_cami/task_class_template.py
dashai_plugin_test_cami-0.0.3.dist-info/METADATA
dashai_plugin_test_cami-0.0.3.dist-info/WHEEL
dashai_plugin_test_cami-0.0.3.dist-info/entry_points.txt
dashai_plugin_test_cami-0.0.3.dist-info/RECORD
