Metadata-Version: 2.3
Name: dashai_plugin_test_cami
Version: 0.0.3
Summary: DashAI Plugin description
Author: c
Author-email: c@gmail.com
Keywords: DashAI,Model
Requires-Python: >=3.8
